{
  "longitudinal_controller": {
    "1": {
          "Kp": 0.5,
          "Kd": 0.5,
          "Ki": 0
    },
    "2": {
          "Kp": 0.75,
          "Kd": 0.5,
          "Ki": 0
    },
    "3": {
          "Kp": 0.5,
          "Kd": 0.75,
          "Ki": 0.0
        }
  },
  "latitudinal_controller": {
    "1": {
          "Kp": 0.8,
          "Kd": 0.2,
          "Ki": 0.1
    },
    "2": {
          "Kp": 0.8,
          "Kd": 0.1,
          "Ki": 0.1
    },
    "3": {
          "Kp": 0.8,
          "Kd": 0.2,
          "Ki": 0.1
        }
  }
}